{
  "id": 5,
  "routeId": 3,
  "regionId": 1,
  "routeNo": "03",
  "routeName": "Bến Thành - Thạnh Xuân",
  "totalScore": 777,
  "ratingCount": 270,
  "rating1Count": 110,
  "rating2Count": 19,
  "rating3Count": 26,
  "rating4Count": 24,
  "rating5Count": 91,
  "lastUpdated": {},
  "timeTableIn": "14400,15000,15600,16200,16740,17280,17820,18360,18900,19380,19860,20340,20760,21180,21600,22020,22440,22860,23280,23700,24120,24540,24960,25380,25800,26220,26640,27060,27480,27960,28440,28920,29400,29880,30360,30840,31320,31800,32280,32760,33240,33720,34200,34680,35160,35640,36120,36600,37080,37560,38040,38520,39000,39480,39960,40380,40800,41220,41640,42060,42480,42900,43320,43740,44160,44580,45000,45420,45840,46260,46680,47100,47520,47940,48360,48780,49200,49620,50040,50460,50880,51300,51720,52140,52560,52980,53400,53820,54240,54660,55080,55500,55920,56340,56760,57180,57600,58020,58440,58860,59280,59700,60120,60540,60960,61380,61800,62220,62640,63060,63480,63900,64320,64740,65160,65580,66000,66420,66840,67320,67800,68280,68760,69240,69780,70320,70860,71460,72180,72900",
  "timeTableOut": "18000,18600,19200,19800,20400,20880,21360,21840,22320,22800,23280,23760,24240,24660,25080,25500,25920,26340,26760,27180,27600,28020,28440,28860,29280,29700,30120,30540,30960,31380,31800,32220,32640,33060,33480,33900,34320,34740,35220,35700,36180,36660,37140,37620,38100,38580,39060,39540,40020,40560,41100,41640,42120,42540,42960,43380,43800,44220,44640,45060,45480,45900,46320,46740,47160,47580,48000,48420,48840,49260,49680,50100,50520,50940,51360,51780,52200,52620,53040,53460,53880,54300,54720,55140,55560,55980,56400,56820,57240,57660,58080,58500,58920,59340,59760,60180,60600,61020,61440,61860,62280,62700,63120,63540,63960,64380,64800,65220,65640,66060,66480,66900,67320,67740,68160,68580,69000,69420,69840,70260,70680,71100,71520,71940,72360,72780,73260,73740,74220,74700",
  "type": "Phổ thông - Có trợ giá",
  "distance": 20600,
  "tickets": null,
  "headway": "7 - 12",
  "operationTime": "04:00 - 20:45",
  "outBoundDescription": "Bãi xe Thạnh Xuân 52 - Đường Thạnh Xuân 52 - Đường Bùi Công Trừng - Đường Hà Huy Giáp - Đường Nguyễn Oanh - Đường Nguyễn Kiệm - Đường Hoàng Minh Giám - Đường Đào Duy Anh - Đường Hồ Văn Huê - Đường Hoàng Văn Thụ - Đường Phan Đình Phùng - Đường Hai Bà Trưng - Đường Tôn Đức Thắng - Đường Hàm Nghi - Đường Lê Lai - Bến xe buýt Sài Gòn",
  "inBoundDescription": "Bến xe buýt Sài Gòn - Đường Phạm Ngũ Lão - Đường Yersin - Đường Trần Hưng Đạo - Đường Hàm Nghi - Đường Hồ Tùng Mậu - Đường nhánh S2 - Đường Tôn Đức Thắng - Đường Hai Bà Trưng - Đường Phan Đình Phùng - Đường Nguyễn Kiệm - Đường Nguyễn Thái Sơn - Đường Phạm Ngũ Lão - Đường Nguyễn Oanh - Đường Hà Huy Giáp - Đường Bùi Công Trừng - Đường Thạnh Xuân 52 - Bãi xe Thạnh Xuân 52",
  "normalTicket": 6,
  "studentTicket": "3.000 VNĐ",
  "monthlyTicket": "135,000 VNĐ",
  "normalTicketNum": 6000,
  "studentTicketNum": 3000,
  "monthlyTicketNum": null,
  "orgs": "Hợp tác xã vận tải 19/5, ĐT: 18001557",
  "timeOfTrip": "55 - 65",
  "totalTrip": "260 [TPD]",
  "routeNoI18n": null,
  "routeNameI18n": null,
  "routeType": 1,
  "privateRoute": false,
  "disabled": false,
  "isTest": null,
  "isDeleted": false,
  "customRoute": null,
  "temporaryClosed": false,
  "underConstruction": false,
  "forwardRouteId": 5,
  "backwardRouteId": 6,
  "forwardBiasDistance": null,
  "backwardBiasDistance": null,
  "isInternalRoute": true,
  "isBuyTicketOnline": true,
  "mirrorRouteId": null,
  "mirrorRouteDirectionReverse": null,
  "color": null,
  "textColor": null,
  "companyId": 28,
  "representInfo": "{\"day\":{\"representPTC1\":{\"name\":\"\",\"position\":\"\"},\"representPTC2\":{\"name\":\"\",\"position\":\"\"},\"representCompany1\":{\"name\":\"\",\"position\":\"\"},\"representCompany2\":{\"name\":\"\",\"position\":\"\"}},\"month\":{\"representPTC1\":{\"name\":\"\",\"position\":\"\"},\"representPTC2\":{\"name\":\"\",\"position\":\"\"},\"representCompany1\":{\"name\":\"\",\"position\":\"\"},\"representCompany2\":{\"name\":\"\",\"position\":\"\"}}}",
  "externalId": null,
  "isDisabledBuyEmvTicket": null,
  "isDisabledBuyQrTicket": null,
  "isNotSubsidized": null,
  "createdAt": {},
  "updatedAt": {},
  "stations": [
    {
      "stationId": 75,
      "stationOrder": 0,
      "stationDirection": 0,
      "routeId": 3,
      "stationName": "Thạnh Xuân",
      "pathPoints": "",
      "stationAddress": "Thửa đất số 413 tờ bản đồ số 04, phường Thạnh Xuân, Quận 12, đường Thạnh Xuân 52, Quận 12",
      "lat": 10.89288,
      "lng": 106.673427,
      "stationType": 1
    },
    {
      "stationId": 3255,
      "stationOrder": 1,
      "stationDirection": 0,
      "routeId": 3,
      "stationName": "Chợ Đường",
      "pathPoints": "106.67342377,10.89288044 106.67333984,10.89335346 106.67724609,10.89455509 106.68105316,10.89550304 106.68466187,10.89676762 106.68881989,10.8986845 106.68901825,10.89791012 106.68904877,10.89745235 106.68904877,10.89745235 106.68904877229167,10.89745200513193",
      "stationAddress": "Đối diện 10 (64/4C), đường Bùi Công Trừng, Quận 12",
      "lat": 10.897452,
      "lng": 106.689048,
      "stationType": 1
    },
    {
      "stationId": 3208,
      "stationOrder": 2,
      "stationDirection": 0,
      "routeId": 3,
      "stationName": "Chùa Báo Ấn",
      "pathPoints": "106.68904877229167,10.89745200513193 106.6890564,10.89630413 106.68848437353554,10.894850246480713",
      "stationAddress": "921, đường Hà Huy Giáp, Quận 12",
      "lat": 10.89485,
      "lng": 106.688485,
      "stationType": 1
    },
    {
      "stationId": 3257,
      "stationOrder": 3,
      "stationDirection": 0,
      "routeId": 3,
      "stationName": "Cầu Phú Long",
      "pathPoints": "106.68848437353554,10.894850246480713 106.68848419,10.89484978 106.68848419,10.89484978 106.68793488,10.89358521 106.6872268219077,10.892612585623308",
      "stationAddress": "793 (đối diện 487A), đường Hà Huy Giáp, Quận 12",
      "lat": 10.892611,
      "lng": 106.687229,
      "stationType": 1
    },
    {
      "stationId": 3205,
      "stationOrder": 4,
      "stationDirection": 0,
      "routeId": 3,
      "stationName": "Cầu Ông Dung",
      "pathPoints": "106.6872268219077,10.892612585623308 106.68722534,10.89261055 106.68722534,10.89261055 106.68649292,10.89162064 106.68576813,10.89050961 106.68523407,10.88933945 106.68510454107175,10.88894515075982",
      "stationAddress": "307/39, đường Hà Huy Giáp, Quận 12",
      "lat": 10.888945,
      "lng": 106.685105,
      "stationType": 1
    },
    {
      "stationId": 3261,
      "stationOrder": 5,
      "stationDirection": 0,
      "routeId": 3,
      "stationName": "Cây xăng Thanh Bình",
      "pathPoints": "106.68510454107175,10.88894515075982 106.68510437,10.88894463 106.68510437,10.88894463 106.68497467,10.8883543 106.68392181,10.88708496 106.68341827,10.88665867 106.6828784357848,10.886327920887343",
      "stationAddress": "22/3, đường Hà Huy Giáp, Quận 12",
      "lat": 10.886327,
      "lng": 106.682879,
      "stationType": 1
    },
    {
      "stationId": 3260,
      "stationOrder": 6,
      "stationDirection": 0,
      "routeId": 3,
      "stationName": "Trường Nguyễn Văn Thệ",
      "pathPoints": "106.6828784357848,10.886327920887343 106.68287659,10.88632679 106.68287659,10.88632679 106.68191528,10.88562107 106.6809082,10.88422966 106.6809082,10.88422966 106.68090750323084,10.884228498431733",
      "stationAddress": "308/27, đường Hà Huy Giáp, Quận 12",
      "lat": 10.88423,
      "lng": 106.680905,
      "stationType": 1
    },
    {
      "stationId": 3262,
      "stationOrder": 7,
      "stationDirection": 0,
      "routeId": 3,
      "stationName": "Trường Điện Lực 2",
      "pathPoints": "106.68090750323084,10.884228498431733 106.68013763,10.88294506 106.67964172,10.88214397 106.67922974,10.88111687 106.67922902545746,10.881115463251707",
      "stationAddress": "327/27, đường Hà Huy Giáp, Quận 12",
      "lat": 10.881117,
      "lng": 106.679226,
      "stationType": 1
    },
    {
      "stationId": 3263,
      "stationOrder": 8,
      "stationDirection": 0,
      "routeId": 3,
      "stationName": "Chợ Thạnh Xuân",
      "pathPoints": "106.67922902545746,10.881115463251707 106.67907715,10.88081646 106.67826843,10.87898254 106.67826843,10.87898254 106.67826794397537,10.87898155190946",
      "stationAddress": "59/2 , đường Hà Huy Giáp, Quận 12",
      "lat": 10.878983,
      "lng": 106.678265,
      "stationType": 1
    },
    {
      "stationId": 204,
      "stationOrder": 9,
      "stationDirection": 0,
      "routeId": 3,
      "stationName": "Ga ra Thanh Hậu",
      "pathPoints": "106.67826794397537,10.87898155190946 106.67771912,10.87786579 106.67740631,10.87706566 106.67721558,10.87658119 106.67700195,10.87611771 106.67671967,10.87507439 106.67671967,10.87507439 106.67671967880254,10.875073992880344",
      "stationAddress": "517-523, đường Hà Huy Giáp, Quận 12",
      "lat": 10.875074,
      "lng": 106.67672,
      "stationType": 1
    },
    {
      "stationId": 205,
      "stationOrder": 10,
      "stationDirection": 0,
      "routeId": 3,
      "stationName": "Vườn kiểng Quang Dũng",
      "pathPoints": "106.67671967880254,10.875073992880344 106.6767883250414,10.87197707370279",
      "stationAddress": "59/4, đường Hà Huy Giáp, Quận 12",
      "lat": 10.871977,
      "lng": 106.676785,
      "stationType": 1
    },
    {
      "stationId": 206,
      "stationOrder": 11,
      "stationDirection": 0,
      "routeId": 3,
      "stationName": "Cây xăng Tài Lộc",
      "pathPoints": "106.6767883250414,10.87197707370279 106.67678833,10.87197685 106.67678833,10.87197685 106.67679596,10.87128067 106.67693329,10.8708334 106.67707062,10.87023258 106.67727661,10.86972713 106.67750549,10.86918449 106.67762756,10.86898994 106.67832184,10.86808872 106.67823029,10.86801529 106.67823029,10.86801529 106.67823029,10.86801529 106.67823287736698,10.868015726654214",
      "stationAddress": "331, đường Hà Huy Giáp, Quận 12",
      "lat": 10.868015,
      "lng": 106.678233,
      "stationType": 1
    },
    {
      "stationId": 207,
      "stationOrder": 12,
      "stationDirection": 0,
      "routeId": 3,
      "stationName": "Đình thần Giao Khẩu",
      "pathPoints": "106.67823287736698,10.868015726654214 106.67838287,10.86804104 106.67956543,10.86679268 106.68014526,10.86584949 106.68034357830852,10.864886530994344",
      "stationAddress": "297, đường Hà Huy Giáp, Quận 12",
      "lat": 10.864886,
      "lng": 106.680341,
      "stationType": 1
    },
    {
      "stationId": 208,
      "stationOrder": 13,
      "stationDirection": 0,
      "routeId": 3,
      "stationName": "Ngã tư Ga",
      "pathPoints": "106.68034357830852,10.864886530994344 106.68034363,10.86488628 106.68034363,10.86488628 106.68034363,10.86488628 106.68042755,10.86470604 106.68036652,10.8637476 106.68004608,10.86121368 106.67990875,10.86001778 106.67980194,10.85888004 106.67964940796826,10.857983930557335",
      "stationAddress": "141-143A, đường Hà Huy Giáp, Quận 12",
      "lat": 10.857984,
      "lng": 106.679649,
      "stationType": 1
    },
    {
      "stationId": 211,
      "stationOrder": 14,
      "stationDirection": 0,
      "routeId": 3,
      "stationName": "Nhà hàng Bến Xưa",
      "pathPoints": "106.67964940796826,10.857983930557335 106.67964935,10.85798359 106.67964935,10.85798359 106.67964935,10.85798359 106.67964935,10.85798359 106.67975616,10.85764694 106.679245,10.85374832 106.67900848,10.85347366",
      "stationAddress": "205, đường Hà Huy Giáp, Quận 12",
      "lat": 10.853474,
      "lng": 106.679006,
      "stationType": 1
    },
    {
      "stationId": 209,
      "stationOrder": 15,
      "stationDirection": 0,
      "routeId": 3,
      "stationName": "Cầu An Lộc",
      "pathPoints": "106.67900848,10.85347366 106.67900848,10.85347366 106.67900848,10.85347366 106.67900848,10.85347366 106.67900848,10.85347366 106.67914581,10.85333729 106.67881012,10.85111427 106.67853552863251,10.848838418835626",
      "stationAddress": "523-525, đường Nguyễn Oanh, Quận Gò Vấp",
      "lat": 10.848838,
      "lng": 106.678539,
      "stationType": 1
    },
    {
      "stationId": 210,
      "stationOrder": 16,
      "stationDirection": 0,
      "routeId": 3,
      "stationName": "Bến Đò",
      "pathPoints": "106.67853552863251,10.848838418835626 106.67853546,10.84883785 106.67853546,10.84883785 106.67853546,10.84883785 106.67853546,10.84883785 106.6785202,10.84788418 106.67841339,10.8469944 106.6782608,10.84701538",
      "stationAddress": "451, đường Nguyễn Oanh, Quận Gò Vấp",
      "lat": 10.847015,
      "lng": 106.67826,
      "stationType": 1
    },
    {
      "stationId": 212,
      "stationOrder": 17,
      "stationDirection": 0,
      "routeId": 3,
      "stationName": "Bưu điện An Nhơn",
      "pathPoints": "106.6782608,10.84701538 106.6782608,10.84701538 106.6782608,10.84701538 106.6782608,10.84701538 106.6782608,10.84701538 106.6783905,10.84695721 106.67730713,10.84393311 106.67721558,10.84397507",
      "stationAddress": "357, đường Nguyễn Oanh, Quận Gò Vấp",
      "lat": 10.843975,
      "lng": 106.677214,
      "stationType": 1
    },
    {
      "stationId": 214,
      "stationOrder": 18,
      "stationDirection": 0,
      "routeId": 3,
      "stationName": "Ngã tư An Nhơn",
      "pathPoints": "106.67721558,10.84397507 106.67721558,10.84397507 106.67721558,10.84397507 106.67721558,10.84397507 106.67721558,10.84397507 106.67727661,10.84382725 106.67640686,10.84142017 106.67631531,10.84143639 106.67631531,10.84143639 106.67631531,10.84143639 106.67631503425798,10.841435421077898",
      "stationAddress": "257, đường Nguyễn Oanh, Quận Gò Vấp",
      "lat": 10.841436,
      "lng": 106.676313,
      "stationType": 1
    },
    {
      "stationId": 215,
      "stationOrder": 19,
      "stationDirection": 0,
      "routeId": 3,
      "stationName": "Đài Liệt sĩ",
      "pathPoints": "106.67631503425798,10.841435421077898 106.67604065,10.84047127 106.67570496,10.83951759 106.67570496,10.83951759 106.67570496,10.83951759 106.675706428,10.839516856000001",
      "stationAddress": "197, đường Nguyễn Oanh, Quận Gò Vấp",
      "lat": 10.839518,
      "lng": 106.675707,
      "stationType": 1
    },
    {
      "stationId": 216,
      "stationOrder": 20,
      "stationDirection": 0,
      "routeId": 3,
      "stationName": "Trường Vinhempic",
      "pathPoints": "106.675706428,10.839516856000001 106.67578888,10.83947563 106.67546844,10.83851719 106.67550659,10.83697319 106.67539499339284,10.836977841483888",
      "stationAddress": "189 (đối diện 234), đường Nguyễn Oanh, Quận Gò Vấp",
      "lat": 10.836978,
      "lng": 106.675395,
      "stationType": 1
    },
    {
      "stationId": 218,
      "stationOrder": 21,
      "stationDirection": 0,
      "routeId": 3,
      "stationName": "Cư xá Lam Sơn",
      "pathPoints": "106.67539499339284,10.836977841483888 106.67539215,10.83697796 106.67539215,10.83697796 106.67539215,10.83697796 106.67544556,10.83681011 106.67544556,10.83553505 106.67553706136967,10.834939316615039",
      "stationAddress": "189 (đối diện A4), đường Nguyễn Oanh, Quận Gò Vấp",
      "lat": 10.834939,
      "lng": 106.675535,
      "stationType": 1
    },
    {
      "stationId": 217,
      "stationOrder": 22,
      "stationDirection": 0,
      "routeId": 3,
      "stationName": "Ngã tư Phan Văn Trị",
      "pathPoints": "106.67553706136967,10.834939316615039 106.67553711,10.834939 106.67553711,10.834939 106.67563629,10.83496571 106.6762619,10.8332634 106.67661285,10.83242035 106.67701721,10.83169937 106.67691803,10.83162975 106.67691803,10.83162975 106.67691803,10.83162975 106.67691898015757,10.831630060683706",
      "stationAddress": "93 (2A), đường Nguyễn Oanh, Quận Gò Vấp",
      "lat": 10.83163,
      "lng": 106.676919,
      "stationType": 1
    },
    {
      "stationId": 220,
      "stationOrder": 23,
      "stationDirection": 0,
      "routeId": 3,
      "stationName": "Cầu vượt ngã sáu Gò Vấp",
      "pathPoints": "106.67691898015757,10.831630060683706 106.67701721,10.83166218 106.6780014,10.83013439 106.67891693,10.82859039 106.67884064,10.82853222",
      "stationAddress": "27-29, đường Nguyễn Oanh, Quận Gò Vấp",
      "lat": 10.828532,
      "lng": 106.678839,
      "stationType": 1
    },
    {
      "stationId": 219,
      "stationOrder": 24,
      "stationDirection": 0,
      "routeId": 3,
      "stationName": "Cầu vượt ngã sáu Gò Vấp",
      "pathPoints": "106.67884064,10.82853222 106.67884064,10.82853222 106.67884064,10.82853222 106.67884064,10.82853222 106.67886353,10.82853794 106.67974854,10.82686234 106.67987823,10.82623482 106.67897034,10.8237381",
      "stationAddress": "1001, đường Nguyễn Kiệm, Quận Gò Vấp",
      "lat": 10.823738,
      "lng": 106.678968,
      "stationType": 1
    },
    {
      "stationId": 221,
      "stationOrder": 25,
      "stationDirection": 0,
      "routeId": 3,
      "stationName": "Bệnh Viện 175",
      "pathPoints": "106.67897034,10.8237381 106.67897034,10.8237381 106.67897034,10.8237381 106.67903137,10.82372665 106.67895508,10.82330608 106.67889404,10.82282066 106.67881775,10.82190418 106.67882538,10.82095051 106.67880249,10.82004929 106.6787262,10.82004356 106.6787262,10.82004356 106.6787262,10.82004356 106.67872703093288,10.820043629345259",
      "stationAddress": "883-885, đường Nguyễn Kiệm, Quận Gò Vấp",
      "lat": 10.820044,
      "lng": 106.678727,
      "stationType": 1
    },
    {
      "stationId": 223,
      "stationOrder": 26,
      "stationDirection": 0,
      "routeId": 3,
      "stationName": "Chợ Tân Sơn Nhất",
      "pathPoints": "106.67872703093288,10.820043629345259 106.67879486,10.82004929 106.67871857,10.81676674 106.67859801822127,10.81677238885864",
      "stationAddress": "79-81, đường Nguyễn Kiệm, Quận Gò Vấp",
      "lat": 10.816772,
      "lng": 106.678598,
      "stationType": 1
    },
    {
      "stationId": 224,
      "stationOrder": 27,
      "stationDirection": 0,
      "routeId": 3,
      "stationName": "Đầu công viên Gia Định",
      "pathPoints": "106.67859801822127,10.81677238885864 106.6785965,10.81677246 106.6785965,10.81677246 106.6785965,10.81677246 106.6785965,10.81677246 106.67871094,10.81678772 106.67873383,10.81628227 106.67865753,10.81446457 106.67824554,10.8138895 106.67776489,10.81336308 106.67768110068016,10.813442106747676",
      "stationAddress": "Rạp xiếc, đường Hoàng Minh Giám, Quận Phú Nhuận",
      "lat": 10.813442,
      "lng": 106.677681,
      "stationType": 1
    },
    {
      "stationId": 225,
      "stationOrder": 28,
      "stationDirection": 0,
      "routeId": 3,
      "stationName": "Cuối công viên Gia Định",
      "pathPoints": "106.67768110068016,10.813442106747676 106.67768097,10.81344223 106.67768097,10.81344223 106.67768097,10.81344223 106.677742,10.81340981 106.67630005,10.8116188 106.67478943,10.80987453 106.67474365,10.80990601",
      "stationAddress": "Đối diện số 5, đường Hoàng Minh Giám, Quận Phú Nhuận",
      "lat": 10.809906,
      "lng": 106.674741,
      "stationType": 1
    },
    {
      "stationId": 226,
      "stationOrder": 29,
      "stationDirection": 0,
      "routeId": 3,
      "stationName": "Đầu Đường Đào Duy Anh",
      "pathPoints": "106.67474365,10.80990601 106.67474365,10.80990601 106.67474365,10.80990601 106.67474365,10.80990601 106.6747818,10.80988026 106.67418671,10.80914783 106.67362976,10.80837822 106.67408752,10.80803013 106.67405714655351,10.80797791475029",
      "stationAddress": "155, đường Đào Duy Anh, Quận Phú Nhuận",
      "lat": 10.807978,
      "lng": 106.674057,
      "stationType": 1
    },
    {
      "stationId": 228,
      "stationOrder": 30,
      "stationDirection": 0,
      "routeId": 3,
      "stationName": "Cuối Đường Đào Duy Anh",
      "pathPoints": "106.67405714655351,10.80797791475029 106.67405701,10.80797768 106.67405701,10.80797768 106.67405701,10.80797768 106.67405701,10.80797768 106.67405701,10.80797768 106.67405701,10.80797768 106.67409515,10.80804062 106.67564392,10.80701351 106.67720795,10.80596447 106.67717743,10.80589104",
      "stationAddress": "7-9, đường Đào Duy Anh, Quận Phú Nhuận",
      "lat": 10.805891,
      "lng": 106.677177,
      "stationType": 1
    },
    {
      "stationId": 230,
      "stationOrder": 31,
      "stationDirection": 0,
      "routeId": 3,
      "stationName": "Ngã ba Đào Duy Anh",
      "pathPoints": "106.67717743,10.80589104 106.67717743,10.80589104 106.67717743,10.80589104 106.67717743,10.80589104 106.67717743,10.80589104 106.67717743,10.80589104 106.67724609,10.80596447 106.67812347,10.80543232 106.67778015,10.80484295 106.67772888561039,10.804857599711339",
      "stationAddress": "129, đường Hồ Văn Huê, Quận Phú Nhuận",
      "lat": 10.804858,
      "lng": 106.677729,
      "stationType": 1
    },
    {
      "stationId": 227,
      "stationOrder": 32,
      "stationDirection": 0,
      "routeId": 3,
      "stationName": "Tháp Nước",
      "pathPoints": "106.67772888561039,10.804857599711339 106.67772675,10.80485821 106.67772675,10.80485821 106.67772675,10.80485821 106.67772675,10.80485821 106.67778015,10.8048315 106.67640686,10.80241299 106.67636871,10.80243397",
      "stationAddress": "43B, đường Hồ Văn Huê, Quận Phú Nhuận",
      "lat": 10.802434,
      "lng": 106.676366,
      "stationType": 1
    },
    {
      "stationId": 229,
      "stationOrder": 33,
      "stationDirection": 0,
      "routeId": 3,
      "stationName": "Trung tâm hội nghị tiệc cưới White Palace",
      "pathPoints": "106.67636871,10.80243397 106.67636871,10.80243397 106.67636871,10.80243397 106.67636871,10.80243397 106.67636871,10.80243397 106.67640686,10.80241299 106.6758194,10.80139637 106.67507935,10.80003643 106.67502594,10.80007362",
      "stationAddress": "1B, đường Hồ Văn Huê, Quận Phú Nhuận",
      "lat": 10.800074,
      "lng": 106.675025,
      "stationType": 1
    },
    {
      "stationId": 232,
      "stationOrder": 34,
      "stationDirection": 0,
      "routeId": 3,
      "stationName": "Ngã tư Phú Nhuận",
      "pathPoints": "106.67502594,10.80007362 106.67502594,10.80007362 106.67502594,10.80007362 106.67502594,10.80007362 106.67502594,10.80007362 106.67508698,10.80005264 106.67491913,10.7997942 106.67490387,10.79957294 106.67935181,10.79918289 106.67935181,10.79908752 106.67935181,10.79908752 106.67935181,10.79908752 106.67935181,10.79908752 106.67935401423702,10.79908759807957",
      "stationAddress": "59, đường Hoàng Văn Thụ, Quận Phú Nhuận",
      "lat": 10.799088,
      "lng": 106.679354,
      "stationType": 1
    },
    {
      "stationId": 4755,
      "stationOrder": 35,
      "stationDirection": 0,
      "routeId": 3,
      "stationName": "Trường Cao đẳng Kinh tế Đối ngoại",
      "pathPoints": "106.67935401423702,10.79908759807957 106.68026733,10.79911995 106.68056488,10.79834461 106.68056488,10.79834461 106.68056488,10.79834461 106.68056697528647,10.79834510467803",
      "stationAddress": "335, đường Phan Đình Phùng, Quận Phú Nhuận",
      "lat": 10.798345,
      "lng": 106.680567,
      "stationType": 1
    },
    {
      "stationId": 4756,
      "stationOrder": 36,
      "stationDirection": 0,
      "routeId": 3,
      "stationName": "Chợ Phú Nhuận",
      "pathPoints": "106.68056697528647,10.79834510467803 106.68063354,10.79836082 106.68109894,10.79730511 106.68156433,10.79624844 106.68188477,10.79586887 106.68264008,10.79524708 106.68260193,10.79519367 106.68260193,10.79519367 106.68260380180587,10.795195341655832",
      "stationAddress": "175-177, đường Phan Đình Phùng, Quận Phú Nhuận",
      "lat": 10.795194,
      "lng": 106.682605,
      "stationType": 1
    },
    {
      "stationId": 4757,
      "stationOrder": 37,
      "stationDirection": 0,
      "routeId": 3,
      "stationName": "Cầu Kiệu",
      "pathPoints": "106.68260380180587,10.795195341655832 106.68265533,10.79524136 106.68331909,10.79471207 106.68398285,10.79418278 106.68465424,10.79365253 106.68531799,10.79312325 106.68527985,10.79308128",
      "stationAddress": "55, đường Phan Đình Phùng, Quận Phú Nhuận",
      "lat": 10.793081,
      "lng": 106.685277,
      "stationType": 1
    },
    {
      "stationId": 231,
      "stationOrder": 38,
      "stationDirection": 0,
      "routeId": 3,
      "stationName": "Trần Quang Khải",
      "pathPoints": "106.68527985,10.79308128 106.68527985,10.79308128 106.68527985,10.79308128 106.68531799,10.79311848 106.68598938,10.79259109 106.68666077,10.79206371 106.68732452,10.79153728 106.68799591,10.7910099 106.68795013,10.79093933",
      "stationAddress": "423 A, đường Hai Bà Trưng, Quận 3",
      "lat": 10.790939,
      "lng": 106.68795,
      "stationType": 1
    },
    {
      "stationId": 234,
      "stationOrder": 39,
      "stationDirection": 0,
      "routeId": 3,
      "stationName": "Chợ Tân Định",
      "pathPoints": "106.68795013,10.79093933 106.68795013,10.79093933 106.68795013,10.79093933 106.68802643,10.79098892 106.68925476,10.79000378 106.69048309,10.78901863 106.69044495,10.7889719 106.69044495,10.7889719 106.69044495,10.7889719 106.69044500836102,10.78897199485579",
      "stationAddress": "295, đường Hai Bà Trưng, Quận 3",
      "lat": 10.788972,
      "lng": 106.690445,
      "stationType": 1
    },
    {
      "stationId": 233,
      "stationOrder": 40,
      "stationDirection": 0,
      "routeId": 3,
      "stationName": "Công viên Lê Văn Tám",
      "pathPoints": "106.69044500836102,10.78897199485579 106.69048309,10.78903389 106.69160461,10.78814125 106.69272614,10.78724766 106.6926513704135,10.78717569304807",
      "stationAddress": "243, đường Hai Bà Trưng, Quận 3",
      "lat": 10.787174,
      "lng": 106.692653,
      "stationType": 1
    },
    {
      "stationId": 235,
      "stationOrder": 41,
      "stationDirection": 0,
      "routeId": 3,
      "stationName": "Trần Cao Vân",
      "pathPoints": "106.6926513704135,10.78717569304807 106.69264984,10.78717422 106.69264984,10.78717422 106.69264984,10.78717422 106.69264984,10.78717422 106.69271851,10.78724766 106.69371796,10.78645992 106.69472504,10.78567219 106.6957016,10.7848711 106.69667816,10.78407001 106.69662476,10.78402328",
      "stationAddress": "157, đường Hai Bà Trưng, Quận 3",
      "lat": 10.784023,
      "lng": 106.696625,
      "stationType": 1
    },
    {
      "stationId": 236,
      "stationOrder": 42,
      "stationDirection": 0,
      "routeId": 3,
      "stationName": "Lê Duẩn",
      "pathPoints": "106.69662476,10.78402328 106.69662476,10.78402328 106.69662476,10.78402328 106.69662476,10.78402328 106.69662476,10.78402328 106.69662476,10.78402328 106.69667053,10.78406525 106.69726563,10.78355408 106.69785309,10.78304291 106.69845581,10.78249931 106.69905853,10.78195667 106.69902039,10.78190994",
      "stationAddress": "Đối diện Lãnh sự quán Pháp, đường Hai Bà Trưng, Quận 1",
      "lat": 10.78191,
      "lng": 106.69902,
      "stationType": 1
    },
    {
      "stationId": 237,
      "stationOrder": 43,
      "stationDirection": 0,
      "routeId": 3,
      "stationName": "Bệnh viện Nhi Đồng 2",
      "pathPoints": "106.69902039,10.78190994 106.69902039,10.78190994 106.69902039,10.78190994 106.69902039,10.78190994 106.69902039,10.78190994 106.69902039,10.78190994 106.69908142,10.78195667 106.6997757,10.78133488 106.70046234,10.78071308 106.70114899,10.78009129 106.70183563,10.77946949 106.70174408,10.77938461 106.70174408,10.77938461 106.70174408,10.77938461 106.70174423457216,10.779384762968197",
      "stationAddress": "Kế 115, đường Hai Bà Trưng, Quận 1",
      "lat": 10.779385,
      "lng": 106.701744,
      "stationType": 1
    },
    {
      "stationId": 238,
      "stationOrder": 44,
      "stationDirection": 0,
      "routeId": 3,
      "stationName": "Nhà Hát Thành Phố",
      "pathPoints": "106.70174423457216,10.779384762968197 106.70183563,10.77947521 106.70269012,10.77870274 106.70354462,10.77793121 106.70350647,10.77787304 106.70350647,10.77787304 106.70350647,10.77787304 106.70350647,10.77787304 106.70350647,10.77787304 106.70350908662505,10.777874566078834",
      "stationAddress": "101, đường Hai Bà Trưng, Quận 1",
      "lat": 10.777873,
      "lng": 106.70351,
      "stationType": 1
    },
    {
      "stationId": 239,
      "stationOrder": 45,
      "stationDirection": 0,
      "routeId": 3,
      "stationName": "Công Trường Mê Linh",
      "pathPoints": "106.70350908662505,10.777874566078834 106.70355225,10.77789974 106.7046051,10.77695942 106.70566559,10.77601814 106.70563507,10.77597618",
      "stationAddress": "Đối diện 2, đường Hai Bà Trưng, Quận 1",
      "lat": 10.775976,
      "lng": 106.705635,
      "stationType": 1
    },
    {
      "stationId": 79,
      "stationOrder": 46,
      "stationDirection": 0,
      "routeId": 3,
      "stationName": "Bến Bạch Đằng",
      "pathPoints": "106.70563507,10.77597618 106.70563507,10.77597618 106.70563507,10.77597618 106.70563507,10.77597618 106.70563507,10.77597618 106.70563507,10.77597618 106.70563507,10.77597618 106.70563507,10.77597618 106.70565796,10.77602291 106.70605469,10.77567005 106.70597076,10.77552795 106.70593262,10.77537537 106.70594025,10.77521706 106.70601654,10.77505398 106.70614624,10.77492142 106.7062912,10.77483749 106.70645905,10.77478504 106.70652771,10.77466869 106.70646667,10.77397823 106.70641327,10.77328777 106.70635986,10.77329922",
      "stationAddress": "21, đường Tôn Đức Thắng, Quận 1",
      "lat": 10.773299,
      "lng": 106.706359,
      "stationType": 1
    },
    {
      "stationId": 76,
      "stationOrder": 47,
      "stationDirection": 0,
      "routeId": 3,
      "stationName": "Cục Hải Quan Thành Phố",
      "pathPoints": "106.70635986,10.77329922 106.70635986,10.77329922 106.70635986,10.77329922 106.70635986,10.77329922 106.70635986,10.77329922 106.70635986,10.77329922 106.70635986,10.77329922 106.70635986,10.77329922 106.70641327,10.77329826 106.70630646,10.77200222 106.70620728,10.77085876 106.70555115,10.77088547 106.70555115,10.77088547 106.70555115,10.77088547 106.70555115,10.77088547 106.70554901907914,10.770885544646807",
      "stationAddress": "2-4, đường Hàm Nghi, Quận 1",
      "lat": 10.770885,
      "lng": 106.705549,
      "stationType": 1
    },
    {
      "stationId": 3691,
      "stationOrder": 48,
      "stationDirection": 0,
      "routeId": 3,
      "stationName": "Chợ Cũ",
      "pathPoints": "106.70554901907914,10.770885544646807 106.70435333,10.77092743 106.70310974,10.77100563 106.70310974,10.77100563 106.703107990596,10.771005681682356",
      "stationAddress": "84, đường Hàm Nghi, Quận 1",
      "lat": 10.771006,
      "lng": 106.703108,
      "stationType": 1
    },
    {
      "stationId": 2028,
      "stationOrder": 49,
      "stationDirection": 0,
      "routeId": 3,
      "stationName": "Trường Cao Thắng",
      "pathPoints": "106.703107990596,10.771005681682356 106.70185299284697,10.771042757875936",
      "stationAddress": "Trường Cao Thắng, đường Hàm Nghi, Quận 1",
      "lat": 10.771043,
      "lng": 106.701853,
      "stationType": 1
    },
    {
      "stationId": 7270,
      "stationOrder": 50,
      "stationDirection": 0,
      "routeId": 3,
      "stationName": "Trạm Trung chuyển trên đường Hàm Nghi",
      "pathPoints": "106.70185299284697,10.771042757875936 106.70185089,10.77104282 106.70185089,10.77104282 106.70089722,10.77106953 106.69995117,10.77109623 106.69995117,10.77109623 106.69995117,10.77109623 106.69994800980086,10.771096325232392",
      "stationAddress": "Hàm Nghi 6, đường Hàm Nghi, Quận 1",
      "lat": 10.771096,
      "lng": 106.699948,
      "stationType": 1
    },
    {
      "stationId": 7273,
      "stationOrder": 51,
      "stationDirection": 0,
      "routeId": 3,
      "stationName": "Khách sạn New World",
      "pathPoints": "106.69994800980086,10.771096325232392 106.69909668,10.77112198 106.69845581,10.77138901 106.69780731,10.77165604 106.69719696,10.77139854 106.69657898,10.77114201 106.69596863,10.77088547 106.69594574,10.77096367",
      "stationAddress": "Số 76, đường Lê Lai, Quận 1",
      "lat": 10.770964,
      "lng": 106.695946,
      "stationType": 1
    },
    {
      "stationId": 7274,
      "stationOrder": 52,
      "stationDirection": 0,
      "routeId": 3,
      "stationName": "Nguyễn Thị Nghĩa",
      "pathPoints": "106.69594574,10.77096367 106.69594574,10.77096367 106.69594574,10.77096367 106.69594574,10.77096367 106.69594574,10.77096367 106.69599152,10.77089024 106.69537354,10.77063179 106.69475555,10.7703743 106.69413757,10.77011585 106.69351959,10.76988888 106.6934967,10.76995182",
      "stationAddress": "94-96, đường Lê Lai, Quận 1",
      "lat": 10.769952,
      "lng": 106.693495,
      "stationType": 1
    },
    {
      "stationId": 7275,
      "stationOrder": 53,
      "stationDirection": 0,
      "routeId": 3,
      "stationName": "Tôn Thất Tùng",
      "pathPoints": "106.6934967,10.76995182 106.6934967,10.76995182 106.6934967,10.76995182 106.6934967,10.76995182 106.6934967,10.76995182 106.6934967,10.76995182 106.69351959,10.76988411 106.69276428,10.7695837 106.69200897,10.76928329 106.69125366,10.76898479 106.69049835,10.76868725 106.69046788893532,10.76876053820381",
      "stationAddress": "202-204, đường Lê Lai, Quận 1",
      "lat": 10.768761,
      "lng": 106.690469,
      "stationType": 1
    },
    {
      "stationId": 35,
      "stationOrder": 54,
      "stationDirection": 0,
      "routeId": 3,
      "stationName": "Bến xe buýt Sài Gòn",
      "pathPoints": "106.69046788893532,10.76876053820381 106.69046783,10.76876068 106.69046783,10.76876068 106.69046783,10.76876068 106.69046783,10.76876068 106.69046783,10.76876068 106.69046783,10.76876068 106.69049835,10.76868725 106.68985748,10.7684164 106.68921661,10.76814461 106.68936157,10.76767635 106.68936157,10.76767635 106.68936157,10.76767635",
      "stationAddress": "BẾN XE BUÝT SÀI GÒN, đường Lê Lai, Quận 1",
      "lat": 10.767676,
      "lng": 106.689362,
      "stationType": 1
    },
    {
      "stationId": 35,
      "stationOrder": 0,
      "stationDirection": 1,
      "routeId": 3,
      "stationName": "Bến xe buýt Sài Gòn",
      "pathPoints": "",
      "stationAddress": "BẾN XE BUÝT SÀI GÒN, đường Lê Lai, Quận 1",
      "lat": 10.767676,
      "lng": 106.689362,
      "stationType": 1
    },
    {
      "stationId": 7276,
      "stationOrder": 1,
      "stationDirection": 1,
      "routeId": 3,
      "stationName": "Tôn Thất Tùng",
      "pathPoints": "106.68936157,10.76767635 106.68936157,10.76767635 106.68955994,10.76718521 106.69024658,10.76744652 106.69093323,10.76770687 106.69094080265455,10.76766995951208",
      "stationAddress": "277-279-275Y, đường Phạm Ngũ Lão, Quận 1",
      "lat": 10.76767,
      "lng": 106.690941,
      "stationType": 1
    },
    {
      "stationId": 7277,
      "stationOrder": 2,
      "stationDirection": 1,
      "routeId": 3,
      "stationName": "Nguyễn Thị Nghĩa",
      "pathPoints": "106.69094080265455,10.76766995951208 106.69094086,10.76766968 106.69094086,10.76766968 106.69094086,10.76766968 106.69091797,10.76771259 106.69160461,10.7679863 106.69229889,10.76826096 106.69299316,10.76853752 106.69367981,10.76881409 106.69370123563652,10.768789987328942",
      "stationAddress": "187, đường Phạm Ngũ Lão, Quận 1",
      "lat": 10.768788,
      "lng": 106.693699,
      "stationType": 1
    },
    {
      "stationId": 7278,
      "stationOrder": 3,
      "stationDirection": 1,
      "routeId": 3,
      "stationName": "Trường Emst Thalmann",
      "pathPoints": "106.69370123563652,10.768789987328942 106.6937027,10.76878834 106.6937027,10.76878834 106.69367218,10.76882458 106.69461823,10.76919365 106.6955719,10.76956272 106.6955870508053,10.769504013111597",
      "stationAddress": "Trường Emst Thalmann, đường Phạm Ngũ Lão, Quận 1",
      "lat": 10.769504,
      "lng": 106.695587,
      "stationType": 1
    },
    {
      "stationId": 7265,
      "stationOrder": 4,
      "stationDirection": 1,
      "routeId": 3,
      "stationName": "Trạm Trung chuyển trên đường Hàm Nghi",
      "pathPoints": "106.6955870508053,10.769504013111597 106.69558716,10.76950359 106.69558716,10.76950359 106.69558716,10.76950359 106.69558716,10.76950359 106.69558716,10.76950359 106.69558716,10.76950359 106.69558716,10.76950359 106.69557953,10.7695837 106.69617462,10.76981544 106.6964798,10.76915169 106.69697571,10.76969433 106.69747162,10.77023697 106.69842529,10.77131748 106.69922638,10.77092171 106.70025635,10.77091122 106.70025635,10.77091122 106.70025635,10.77091122 106.70025635,10.77091122 106.70025635,10.77091122 106.70025635,10.77091122 106.70025900436879,10.770911132441563",
      "stationAddress": "Hàm nghi 5, đường Hàm Nghi, Quận 1",
      "lat": 10.770911,
      "lng": 106.700259,
      "stationType": 1
    },
    {
      "stationId": 7693,
      "stationOrder": 5,
      "stationDirection": 1,
      "routeId": 3,
      "stationName": "Nam Kỳ Khởi Nghĩa",
      "pathPoints": "106.70025900436879,10.770911132441563 106.70135400040617,10.77087501231341",
      "stationAddress": "93-95, đường Hàm Nghi, Quận 1",
      "lat": 10.770875,
      "lng": 106.701354,
      "stationType": 1
    },
    {
      "stationId": 1256,
      "stationOrder": 6,
      "stationDirection": 1,
      "routeId": 3,
      "stationName": "Chợ Cũ",
      "pathPoints": "106.70135400040617,10.77087501231341 106.70135498,10.77087498 106.70135498,10.77087498 106.70199585,10.77081108 106.70199585,10.77081108 106.70199800049255,10.770811016745343",
      "stationAddress": "89A, đường Hàm Nghi, Quận 1",
      "lat": 10.770811,
      "lng": 106.701998,
      "stationType": 1
    },
    {
      "stationId": 7588,
      "stationOrder": 7,
      "stationDirection": 1,
      "routeId": 3,
      "stationName": "Giao lộ Hàm Nghi - Tôn Thất Đạm",
      "pathPoints": "106.70199800049255,10.770811016745343 106.70251465,10.77079582 106.70303799091997,10.770779705119935",
      "stationAddress": "81-83-83B, đường Hàm Nghi, Quận 1",
      "lat": 10.77078,
      "lng": 106.703038,
      "stationType": 1
    },
    {
      "stationId": 32,
      "stationOrder": 8,
      "stationDirection": 1,
      "routeId": 3,
      "stationName": "Hồ Tùng Mậu",
      "pathPoints": "106.70303799091997,10.770779705119935 106.70304108,10.77077961 106.70304108,10.77077961 106.70355225,10.770751 106.70407104,10.77072239",
      "stationAddress": "67, đường Hàm Nghi, Quận 1",
      "lat": 10.770722,
      "lng": 106.704074,
      "stationType": 1
    },
    {
      "stationId": 31,
      "stationOrder": 9,
      "stationDirection": 1,
      "routeId": 3,
      "stationName": "Bến Bạch Đằng",
      "pathPoints": "106.70407104,10.77072239 106.70407104,10.77072239 106.70407104,10.77072239 106.70407104,10.77074814 106.70454407,10.77073193 106.70475769,10.77024746 106.70497894,10.76976299 106.70510864,10.76949883 106.70529175,10.76943016 106.70561218,10.76948547 106.70593262,10.76953983 106.70606995,10.76959991 106.7061615,10.76972961 106.70639038,10.77054977 106.70635986,10.77071953 106.70633698,10.77099037 106.70639038,10.77161789 106.70644379,10.77224064 106.70649719,10.77286434 106.7065506,10.77348709 106.706604,10.77410984 106.70665418478843,10.774094608855638",
      "stationAddress": "Bến thủy nội địa Thủ Thiêm, đường Tôn Đức Thắng, Quận 1",
      "lat": 10.774094,
      "lng": 106.706654,
      "stationType": 1
    },
    {
      "stationId": 34,
      "stationOrder": 10,
      "stationDirection": 1,
      "routeId": 3,
      "stationName": "Công Trường Mê Linh",
      "pathPoints": "106.70665418478843,10.774094608855638 106.70665741,10.77409363 106.70665741,10.77409363 106.70665741,10.77409363 106.70665741,10.77409363 106.70664978,10.77411556 106.70661163,10.77409935 106.70666504,10.77487469 106.70671844,10.77564907 106.70659637,10.77582264 106.70631409,10.77583313 106.70607758,10.77570152 106.70578766,10.77595997 106.70582581,10.77599716 106.70582581,10.77599716 106.70582581,10.77599716 106.70582581,10.77599716 106.70582581,10.77599716 106.70582581,10.77599716 106.7058234364254,10.775995231794695",
      "stationAddress": "2, đường Hai Bà Trưng, Quận 1",
      "lat": 10.775997,
      "lng": 106.705822,
      "stationType": 1
    },
    {
      "stationId": 42,
      "stationOrder": 11,
      "stationDirection": 1,
      "routeId": 3,
      "stationName": "Nhà Hát Thành Phố",
      "pathPoints": "106.7058234364254,10.775995231794695 106.70578003,10.77595997 106.70518494,10.77649021 106.70458984,10.7770195 106.7040329,10.7774992 106.7035141,10.77800465 106.7035590710397,10.778030878194844",
      "stationAddress": "74/A2-74/A4, đường Hai Bà Trưng, Quận 1",
      "lat": 10.778031,
      "lng": 106.703559,
      "stationType": 1
    },
    {
      "stationId": 44,
      "stationOrder": 12,
      "stationDirection": 1,
      "routeId": 3,
      "stationName": "Bệnh viện Nhi Đồng 2",
      "pathPoints": "106.7035590710397,10.778030878194844 106.70355988,10.77803135 106.70355988,10.77803135 106.70355988,10.77803135 106.70355988,10.77803135 106.70355988,10.77803135 106.70355988,10.77803135 106.70355988,10.77803135 106.70355988,10.77803135 106.70355988,10.77803135 106.70355988,10.77803135 106.70355988,10.77803135 106.70352173,10.77799416 106.70300293,10.77846813 106.70249939,10.77892685 106.70198822,10.77938271 106.70149231,10.77984905 106.70153809,10.77988052 106.70153809,10.77988052 106.70153809,10.77988052 106.70153809,10.77988052 106.70153809,10.77988052 106.70153809,10.77988052 106.70153809,10.77988052 106.70153658194775,10.779879792938674",
      "stationAddress": "Đối diện 115Ter, đường Hai Bà Trưng, Quận 1",
      "lat": 10.779881,
      "lng": 106.701536,
      "stationType": 1
    },
    {
      "stationId": 39,
      "stationOrder": 13,
      "stationDirection": 1,
      "routeId": 3,
      "stationName": "Bưu Điện Thành Phố",
      "pathPoints": "106.70153658194775,10.779879792938674 106.70148468,10.77985477 106.70063019,10.78061295 106.70067381441156,10.78064385022772",
      "stationAddress": "86, đường Hai Bà Trưng, Quận 1",
      "lat": 10.780645,
      "lng": 106.700673,
      "stationType": 1
    },
    {
      "stationId": 41,
      "stationOrder": 14,
      "stationDirection": 1,
      "routeId": 3,
      "stationName": "Sở Công Thương",
      "pathPoints": "106.70067381441156,10.78064385022772 106.70067596,10.78064537 106.70067596,10.78064537 106.70063019,10.78060818 106.70011902,10.78105831 106.69962311,10.7815094 106.69884491,10.78220463 106.69808197,10.78285789 106.69700623,10.78380966 106.6964798,10.78425503 106.69652557,10.78429699",
      "stationAddress": "142, đường Hai Bà Trưng, Quận 1",
      "lat": 10.784297,
      "lng": 106.696526,
      "stationType": 1
    },
    {
      "stationId": 43,
      "stationOrder": 15,
      "stationDirection": 1,
      "routeId": 3,
      "stationName": "Công viên Lê Văn Tám",
      "pathPoints": "106.69652557,10.78429699 106.69652557,10.78429699 106.69652557,10.78429699 106.69652557,10.78429699 106.69650269,10.78425503 106.69552612,10.78505325 106.69454956,10.78585148 106.69355774,10.78662586 106.69256592,10.78740025 106.69259644,10.78742695",
      "stationAddress": "Đối diện 245, đường Hai Bà Trưng, Quận 1",
      "lat": 10.787427,
      "lng": 106.692599,
      "stationType": 1
    },
    {
      "stationId": 46,
      "stationOrder": 16,
      "stationDirection": 1,
      "routeId": 3,
      "stationName": "Nhà thờ Tân Định",
      "pathPoints": "106.69259644,10.78742695 106.69259644,10.78742695 106.69259644,10.78742695 106.69259644,10.78742695 106.69256592,10.78739548 106.69146729,10.78828621 106.69036102,10.78917599 106.6903990421039,10.789214958919075",
      "stationAddress": "298, đường Hai Bà Trưng, Quận 1",
      "lat": 10.789215,
      "lng": 106.690399,
      "stationType": 1
    },
    {
      "stationId": 47,
      "stationOrder": 17,
      "stationDirection": 1,
      "routeId": 3,
      "stationName": "Chợ Tân Định",
      "pathPoints": "106.6903990421039,10.789214958919075 106.69039917,10.78921509 106.69039917,10.78921509 106.69036865,10.7891655 106.68958282,10.78979015 106.688797,10.79041481 106.68884277,10.79045582",
      "stationAddress": "372-374, đường Hai Bà Trưng, Quận 1",
      "lat": 10.790456,
      "lng": 106.688843,
      "stationType": 1
    },
    {
      "stationId": 45,
      "stationOrder": 18,
      "stationDirection": 1,
      "routeId": 3,
      "stationName": "Cầu Kiệu",
      "pathPoints": "106.68884277,10.79045582 106.68884277,10.79045582 106.68884277,10.79045582 106.68878937,10.79040909 106.6876297,10.79132652 106.68674469,10.79202747 106.68634796,10.79232788 106.68579102,10.79277992 106.68476868,10.79360294 106.68480682,10.79364967",
      "stationAddress": "28 - 30, đường Phan Đình Phùng, Quận Phú Nhuận",
      "lat": 10.79365,
      "lng": 106.68481,
      "stationType": 1
    },
    {
      "stationId": 49,
      "stationOrder": 19,
      "stationDirection": 1,
      "routeId": 3,
      "stationName": "Chợ Phú Nhuận",
      "pathPoints": "106.68480682,10.79364967 106.68480682,10.79364967 106.68480682,10.79364967 106.68476868,10.79360771 106.68387604,10.79431152 106.6829834,10.79501534 106.68302155,10.79506207 106.68302155,10.79506207 106.68301933353449,10.795060315419176",
      "stationAddress": "158 - 160, đường Phan Đình Phùng, Quận Phú Nhuận",
      "lat": 10.795062,
      "lng": 106.683018,
      "stationType": 1
    },
    {
      "stationId": 48,
      "stationOrder": 20,
      "stationDirection": 1,
      "routeId": 3,
      "stationName": "Trường Cao đẳng Kinh tế Đối ngoại",
      "pathPoints": "106.68301933353449,10.795060315419176 106.68297577,10.79502583 106.68218994,10.79562092 106.68169403,10.79607964 106.68146515,10.79653835 106.68123627,10.79699612 106.6810379,10.79746532 106.68084717,10.79793453 106.68090523771225,10.797949049306718",
      "stationAddress": "312 - 314, đường Phan Đình Phùng, Quận Phú Nhuận",
      "lat": 10.79795,
      "lng": 106.680905,
      "stationType": 1
    },
    {
      "stationId": 50,
      "stationOrder": 21,
      "stationDirection": 1,
      "routeId": 3,
      "stationName": "Ngã tư Phú Nhuận",
      "pathPoints": "106.68090523771225,10.797949049306718 106.6809082,10.79794979 106.6809082,10.79794979 106.68084717,10.79792404 106.68065643,10.79836559 106.68045807,10.79880714 106.68026733,10.7992487 106.6800766,10.79969025 106.68013763,10.79971313",
      "stationAddress": "392, đường Nguyễn Kiệm, Quận Phú Nhuận",
      "lat": 10.799713,
      "lng": 106.680138,
      "stationType": 1
    },
    {
      "stationId": 51,
      "stationOrder": 22,
      "stationDirection": 1,
      "routeId": 3,
      "stationName": "Nhà Truyền Thông",
      "pathPoints": "106.68013763,10.79971313 106.68013763,10.79971313 106.68013763,10.79971313 106.68013763,10.79971313 106.68013763,10.79971313 106.68013763,10.79971313 106.6800766,10.79971027 106.67979431,10.80042171 106.67943573,10.80121231 106.6792984,10.80171776 106.6791687,10.80222321 106.679245,10.80223179",
      "stationAddress": "466, đường Nguyễn Kiệm, Quận Phú Nhuận",
      "lat": 10.802232,
      "lng": 106.679245,
      "stationType": 1
    },
    {
      "stationId": 52,
      "stationOrder": 23,
      "stationDirection": 1,
      "routeId": 3,
      "stationName": "Ngã ba Hồ Văn Huê",
      "pathPoints": "106.679245,10.80223179 106.679245,10.80223179 106.679245,10.80223179 106.679245,10.80223179 106.679245,10.80223179 106.679245,10.80223179 106.679245,10.80223179 106.679245,10.80223179 106.679245,10.80223179 106.67916107,10.80221844 106.679039,10.80297756 106.67892456,10.80373573 106.67880249,10.80449486 106.67868042,10.80525303 106.67875671,10.80525875",
      "stationAddress": "582, đường Nguyễn Kiệm, Quận Phú Nhuận",
      "lat": 10.805259,
      "lng": 106.678759,
      "stationType": 1
    },
    {
      "stationId": 53,
      "stationOrder": 24,
      "stationDirection": 1,
      "routeId": 3,
      "stationName": "Coop Mart Nguyễn Kiệm",
      "pathPoints": "106.67875671,10.80525875 106.67875671,10.80525875 106.67875671,10.80525875 106.67875671,10.80525875 106.67875671,10.80525875 106.67875671,10.80525875 106.67875671,10.80525875 106.67875671,10.80525875 106.67875671,10.80525875 106.67875671,10.80525875 106.67868042,10.80525875 106.67857361,10.8059206 106.6784668,10.8065815 106.67843628,10.80707645 106.67852783,10.80707741",
      "stationAddress": "668-670, đường Nguyễn Kiệm, Quận Phú Nhuận",
      "lat": 10.807077,
      "lng": 106.678528,
      "stationType": 1
    },
    {
      "stationId": 54,
      "stationOrder": 25,
      "stationDirection": 1,
      "routeId": 3,
      "stationName": "Chùa Vạn Hạnh",
      "pathPoints": "106.67852783,10.80707741 106.67852783,10.80707741 106.67852783,10.80707741 106.67852783,10.80707741 106.67852783,10.80707741 106.67852783,10.80707741 106.67852783,10.80707741 106.67845154,10.80708694 106.67845917,10.80825329 106.6784668,10.80941963 106.67848206,10.810359 106.67855835,10.81034946",
      "stationAddress": "750, đường Nguyễn Kiệm, Quận Phú Nhuận",
      "lat": 10.810349,
      "lng": 106.67856,
      "stationType": 1
    },
    {
      "stationId": 55,
      "stationOrder": 26,
      "stationDirection": 1,
      "routeId": 3,
      "stationName": "Trường Cao đẳng Hải Quan",
      "pathPoints": "106.67855835,10.81034946 106.67855835,10.81034946 106.67855835,10.81034946 106.67855835,10.81034946 106.67855835,10.81034946 106.67855835,10.81034946 106.67848969,10.81034851 106.67852783,10.81088066 106.67855835,10.81141376 106.6785965,10.81194592 106.67862701,10.81247807 106.67871094,10.8124752",
      "stationAddress": "780A, đường Nguyễn Kiệm, Quận Gò Vấp",
      "lat": 10.812475,
      "lng": 106.678711,
      "stationType": 1
    },
    {
      "stationId": 56,
      "stationOrder": 27,
      "stationDirection": 1,
      "routeId": 3,
      "stationName": "Cầu vượt Nguyễn Thái Sơn - Nguyễn Kiệm",
      "pathPoints": "106.67871094,10.8124752 106.67871094,10.8124752 106.67871094,10.8124752 106.67871094,10.8124752 106.67871094,10.8124752 106.67871094,10.8124752 106.67871094,10.8124752 106.67871094,10.8124752 106.67864227,10.81247807 106.67871857,10.81360531 106.6789856,10.81373692 106.67904663,10.81398964 106.67899323,10.81425858 106.67886353,10.81435871 106.67963409,10.81533146 106.68040466,10.81630325 106.68044281,10.81628227",
      "stationAddress": "86 - 86C, đường Nguyễn Thái Sơn, Quận Gò Vấp",
      "lat": 10.816282,
      "lng": 106.680443,
      "stationType": 1
    },
    {
      "stationId": 57,
      "stationOrder": 28,
      "stationDirection": 1,
      "routeId": 3,
      "stationName": "Ngã ba Phạm Ngũ Lão",
      "pathPoints": "106.68044281,10.81628227 106.68044281,10.81628227 106.68044281,10.81628227 106.68044281,10.81628227 106.6803894,10.81630802 106.6811142,10.8171463 106.6817627,10.8180151 106.68244171,10.81887436 106.68312073,10.81972313 106.68314362,10.81971169",
      "stationAddress": "182, đường Nguyễn Thái Sơn, Quận Gò Vấp",
      "lat": 10.819712,
      "lng": 106.683147,
      "stationType": 1
    },
    {
      "stationId": 60,
      "stationOrder": 29,
      "stationDirection": 1,
      "routeId": 3,
      "stationName": "Cầu vượt ngã sáu Gò Vấp",
      "pathPoints": "106.68314362,10.81971169 106.68314362,10.81971169 106.68314362,10.81971169 106.68314362,10.81971169 106.68314362,10.81971169 106.68314362,10.81971169 106.68310547,10.81975937 106.68350983,10.82029724 106.68321991,10.82083321 106.68293762,10.82136917 106.68264771,10.82190514 106.68235779,10.8224411 106.68206024,10.82297611 106.6817627,10.82351112 106.68146515,10.82404613 106.6811676,10.82458115 106.68122101,10.8246069",
      "stationAddress": "140-142, đường Phạm Ngũ Lão , Quận Gò Vấp",
      "lat": 10.824607,
      "lng": 106.681221,
      "stationType": 1
    },
    {
      "stationId": 58,
      "stationOrder": 30,
      "stationDirection": 1,
      "routeId": 3,
      "stationName": "Cầu vượt ngã sáu Gò Vấp",
      "pathPoints": "106.68122101,10.8246069 106.68122101,10.8246069 106.68122101,10.8246069 106.68122101,10.8246069 106.68122101,10.8246069 106.68122101,10.8246069 106.6811676,10.82458591 106.68087769,10.82513905 106.68058014,10.82569218 106.68029022,10.82624531 106.68000031,10.82679939 106.67967987,10.82734203 106.67935944,10.82788467 106.679039,10.82842731 106.67871857,10.82896996 106.67877197,10.82899094",
      "stationAddress": "110-112, đường Nguyễn Oanh, Quận Gò Vấp",
      "lat": 10.828991,
      "lng": 106.678775,
      "stationType": 1
    },
    {
      "stationId": 62,
      "stationOrder": 31,
      "stationDirection": 1,
      "routeId": 3,
      "stationName": "Ngã tư Phan Văn Trị",
      "pathPoints": "106.67877197,10.82899094 106.67877197,10.82899094 106.67877197,10.82899094 106.67877197,10.82899094 106.67877197,10.82899094 106.67877197,10.82899094 106.67877197,10.82899094 106.67877197,10.82899094 106.67871857,10.82897472 106.67827606,10.82972717 106.67783356,10.83047962 106.67736053,10.83122349 106.67688751,10.83196735 106.67662048,10.8324995 106.67669678,10.83254719",
      "stationAddress": "152, đường Nguyễn Oanh, Quận Gò Vấp",
      "lat": 10.832547,
      "lng": 106.676699,
      "stationType": 1
    },
    {
      "stationId": 67,
      "stationOrder": 32,
      "stationDirection": 1,
      "routeId": 3,
      "stationName": "Cư xá Lam Sơn",
      "pathPoints": "106.67669678,10.83254719 106.67669678,10.83254719 106.67669678,10.83254719 106.67669678,10.83254719 106.67669678,10.83254719 106.67669678,10.83254719 106.67669678,10.83254719 106.67669678,10.83254719 106.67661285,10.83252048 106.6763916,10.83307076 106.67618561,10.83359909 106.67597198,10.83414555 106.67575836,10.834692 106.67556,10.83538723 106.67552948,10.83611393 106.67561,10.83611393",
      "stationAddress": "214, đường Nguyễn Oanh, Quận Gò Vấp",
      "lat": 10.836114,
      "lng": 106.67561,
      "stationType": 1
    },
    {
      "stationId": 63,
      "stationOrder": 33,
      "stationDirection": 1,
      "routeId": 3,
      "stationName": "Đài Liệt sĩ",
      "pathPoints": "106.67561,10.83611393 106.6756134,10.83611393 106.6756134,10.83611393 106.6756134,10.83611393 106.6756134,10.83611393 106.6756134,10.83611393 106.67553711,10.83610916 106.67554474,10.83660698 106.67554474,10.8371048 106.67555237,10.83760262 106.67555237,10.83810043 106.6756134,10.83869553 106.6757431,10.83929634 106.67582703,10.83929729",
      "stationAddress": "Đối diện 197 (93), đường Nguyễn Oanh, Quận Gò Vấp",
      "lat": 10.839297,
      "lng": 106.67583,
      "stationType": 1
    },
    {
      "stationId": 72,
      "stationOrder": 34,
      "stationDirection": 1,
      "routeId": 3,
      "stationName": "Ngã tư An Nhơn",
      "pathPoints": "106.67582703,10.83929729 106.67582703,10.83929729 106.67582703,10.83929729 106.67582703,10.83929729 106.67575836,10.83931732 106.6760025,10.84005547 106.67622375,10.84079266 106.67647552,10.8415432 106.67672729,10.84229469 106.67683306291856,10.84226825172135",
      "stationAddress": "388, đường Nguyễn Oanh, Quận Gò Vấp",
      "lat": 10.842268,
      "lng": 106.676833,
      "stationType": 1
    },
    {
      "stationId": 64,
      "stationOrder": 35,
      "stationDirection": 1,
      "routeId": 3,
      "stationName": "Bến Đò",
      "pathPoints": "106.67683306291856,10.84226825172135 106.67683411,10.84226799 106.67683411,10.84226799 106.67683411,10.84226799 106.67676544,10.84230518 106.67717743,10.84346008 106.67758942,10.84461594 106.6780014,10.84577084 106.67841339,10.84692574 106.67849731,10.84691048 106.67849731,10.84691048 106.67849731,10.84691048 106.67849731,10.84691048 106.67849607049372,10.846910620758996",
      "stationAddress": "538, đường Nguyễn Oanh, Quận Gò Vấp",
      "lat": 10.84691,
      "lng": 106.678496,
      "stationType": 1
    },
    {
      "stationId": 4754,
      "stationOrder": 36,
      "stationDirection": 1,
      "routeId": 3,
      "stationName": "Cầu An Lộc",
      "pathPoints": "106.67849607049372,10.846910620758996 106.67841339,10.84692001 106.67852783,10.84746552 106.67863464,10.84801102 106.67868042,10.84856701 106.6787262,10.849123 106.67880249,10.84911728 106.67880249,10.84911728 106.67880249,10.84911728 106.678802,10.84911728",
      "stationAddress": "604, đường Nguyễn Oanh, Quận Gò Vấp",
      "lat": 10.849117,
      "lng": 106.678802,
      "stationType": 1
    },
    {
      "stationId": 73,
      "stationOrder": 37,
      "stationDirection": 1,
      "routeId": 3,
      "stationName": "Nhà hàng Bến Xưa",
      "pathPoints": "106.678802,10.84911728 106.6787262,10.84911728 106.67879486,10.85010815 106.67899323,10.85145092 106.67914581,10.85265732 106.67928314,10.85264206",
      "stationAddress": "42, đường Hà Huy Giáp, Quận 12",
      "lat": 10.852642,
      "lng": 106.679285,
      "stationType": 1
    },
    {
      "stationId": 213,
      "stationOrder": 38,
      "stationDirection": 1,
      "routeId": 3,
      "stationName": "Ngã tư Ga",
      "pathPoints": "106.67928314,10.85264206 106.67928314,10.85264206 106.67928314,10.85264206 106.67914581,10.85266304 106.67949677,10.85499191 106.67961884,10.85616112 106.67979431,10.85734653 106.67990875,10.85733128 106.67990875,10.85733128 106.67990875,10.85733128 106.67990704003341,10.857331436741957",
      "stationAddress": "154, đường Hà Huy Giáp, Quận 12",
      "lat": 10.857331,
      "lng": 106.679907,
      "stationType": 1
    },
    {
      "stationId": 68,
      "stationOrder": 39,
      "stationDirection": 1,
      "routeId": 3,
      "stationName": "Đình thần Giao Khẩu",
      "pathPoints": "106.67990704003341,10.857331436741957 106.67979431,10.85734177 106.67985535,10.857934 106.67990875,10.85852718 106.67998505,10.85905838 106.68006134,10.85959053 106.68014526,10.86023712 106.68022919,10.86088467 106.68032074,10.86153126 106.68040466,10.86217785 106.68047333,10.86284733 106.68054199,10.86351585 106.68057251,10.86390591 106.68052673,10.86423779 106.68051147,10.864501 106.68045807,10.86481667 106.68035889,10.86520195 106.68043304347778,10.865216782639546",
      "stationAddress": "332, đường Hà Huy Giáp, Quận 12",
      "lat": 10.865217,
      "lng": 106.680433,
      "stationType": 1
    },
    {
      "stationId": 74,
      "stationOrder": 40,
      "stationDirection": 1,
      "routeId": 3,
      "stationName": "Cây xăng Tài Lộc",
      "pathPoints": "106.68043304347778,10.865216782639546 106.68043518,10.86521721 106.68043518,10.86521721 106.68043518,10.86521721 106.68043518,10.86521721 106.68037415,10.86522293 106.68018341,10.86568928 106.68000031,10.86615562 106.67974091,10.86657715 106.67927551,10.86717224 106.67823029,10.86824703 106.6783199255049,10.86830865379769",
      "stationAddress": "408B, đường Hà Huy Giáp, Quận 12",
      "lat": 10.86831,
      "lng": 106.678319,
      "stationType": 1
    },
    {
      "stationId": 69,
      "stationOrder": 41,
      "stationDirection": 1,
      "routeId": 3,
      "stationName": "Vườn kiểng Quang Dũng",
      "pathPoints": "106.6783199255049,10.86830865379769 106.67832184,10.86830997 106.67832184,10.86830997 106.67832184,10.86830997 106.67824554,10.86823654 106.67757416,10.86903667 106.67727661,10.86964798 106.67698669,10.87051201 106.67690277,10.87136555 106.67697906,10.87137127 106.67697906,10.87137127 106.6769779849677,10.871371180440072",
      "stationAddress": "452, đường Hà Huy Giáp, Quận 12",
      "lat": 10.871371,
      "lng": 106.676978,
      "stationType": 1
    },
    {
      "stationId": 70,
      "stationOrder": 42,
      "stationDirection": 1,
      "routeId": 3,
      "stationName": "Ga ra Thanh Hậu",
      "pathPoints": "106.6769779849677,10.871371180440072 106.6769104,10.87136555 106.67684174,10.87226677 106.67684174,10.87316227 106.67681122,10.87417889 106.67680359,10.87517452 106.67689514,10.87549591 106.67703247,10.87545395 106.67703247,10.87545395 106.67703202025876,10.875454073672207",
      "stationAddress": "508, đường Hà Huy Giáp, Quận 12",
      "lat": 10.875454,
      "lng": 106.677032,
      "stationType": 1
    },
    {
      "stationId": 71,
      "stationOrder": 43,
      "stationDirection": 1,
      "routeId": 3,
      "stationName": "Chợ Thạnh Xuân",
      "pathPoints": "106.67703202025876,10.875454073672207 106.67687988,10.87549591 106.67700958,10.87596989 106.67757416,10.87722874 106.67813873,10.87851429 106.67819977,10.87849331",
      "stationAddress": "Nhà văn hóa P. Thạnh Lộc, đường Hà Huy Giáp, Quận 12",
      "lat": 10.878493,
      "lng": 106.678201,
      "stationType": 1
    },
    {
      "stationId": 77,
      "stationOrder": 44,
      "stationDirection": 1,
      "routeId": 3,
      "stationName": "Trường Điện lực 2",
      "pathPoints": "106.67819977,10.87849331 106.67819977,10.87849331 106.67819977,10.87849331 106.67819977,10.87849331 106.6781311,10.87850857 106.67864227,10.87965202 106.67915344,10.88079548 106.67918824979327,10.88078590844741",
      "stationAddress": "554 , đường Hà Huy Giáp, Quận 12",
      "lat": 10.880785,
      "lng": 106.679188,
      "stationType": 1
    },
    {
      "stationId": 3204,
      "stationOrder": 45,
      "stationDirection": 1,
      "routeId": 3,
      "stationName": "Trường Nguyễn Văn Thệ",
      "pathPoints": "106.67918824979327,10.88078590844741 106.67919159,10.88078499 106.67919159,10.88078499 106.67913055,10.88080597 106.67980957,10.88229179 106.68049622,10.88341904 106.68126678,10.88459396 106.6812973,10.88456154 106.6812973,10.88456154 106.68129610772897,10.884562195842845",
      "stationAddress": "628B, đường Hà Huy Giáp, Quận 12",
      "lat": 10.884562,
      "lng": 106.681296,
      "stationType": 1
    },
    {
      "stationId": 3203,
      "stationOrder": 46,
      "stationDirection": 1,
      "routeId": 3,
      "stationName": "Cây xăng Thanh Bình",
      "pathPoints": "106.68129610772897,10.884562195842845 106.68125916,10.88458252 106.68188477,10.88555717 106.68300629,10.88631058 106.68305143183076,10.886254145314474",
      "stationAddress": "704, đường Hà Huy Giáp, Quận 12",
      "lat": 10.886253,
      "lng": 106.68305,
      "stationType": 1
    },
    {
      "stationId": 3206,
      "stationOrder": 47,
      "stationDirection": 1,
      "routeId": 3,
      "stationName": "Cầu Ông Dung",
      "pathPoints": "106.68305143183076,10.886254145314474 106.68305206,10.88625336 106.68305206,10.88625336 106.68300629,10.88631058 106.68345642,10.8866272 106.68399811,10.88710022 106.68428802,10.88745022 106.68500519,10.88832283 106.68513489,10.88877583 106.68519592,10.88877583 106.68518829,10.88875961 106.68518511504844,10.88876044005764",
      "stationAddress": "1/111, đường Hà Huy Giáp, Quận 12",
      "lat": 10.88876,
      "lng": 106.685185,
      "stationType": 1
    },
    {
      "stationId": 3259,
      "stationOrder": 48,
      "stationDirection": 1,
      "routeId": 3,
      "stationName": "Cầu Phú Long",
      "pathPoints": "106.68518511504844,10.88876044005764 106.68510437,10.88878155 106.68530273,10.88943958 106.68572998,10.89028835 106.68622589,10.89112568 106.68693542,10.89213657 106.68703205287186,10.892080825137338",
      "stationAddress": "856, đường Hà Huy Giáp, Quận 12",
      "lat": 10.892079,
      "lng": 106.687031,
      "stationType": 1
    },
    {
      "stationId": 3207,
      "stationOrder": 49,
      "stationDirection": 1,
      "routeId": 3,
      "stationName": "Chùa Báo Ấn",
      "pathPoints": "106.68703205287186,10.892080825137338 106.68703461,10.89207935 106.68703461,10.89207935 106.68703461,10.89207935 106.68694305,10.89215279 106.68745422,10.89278507 106.68790436,10.89341736 106.68824768,10.89413834 106.68856049,10.89488125 106.68861934933426,10.894861016199693",
      "stationAddress": "938, đường Hà Huy Giáp, Quận 12",
      "lat": 10.89486,
      "lng": 106.688619,
      "stationType": 1
    },
    {
      "stationId": 3210,
      "stationOrder": 50,
      "stationDirection": 1,
      "routeId": 3,
      "stationName": "Chợ Đường",
      "pathPoints": "106.68861934933426,10.894861016199693 106.68862152,10.89486027 106.68862152,10.89486027 106.68862152,10.89486027 106.68854523,10.89489174 106.68900299,10.89597988 106.68914032,10.89640045 106.68907166,10.89661503 106.68909454,10.89743614 106.68907928,10.89772034 106.6891009899967,10.897721241026513",
      "stationAddress": "18, đường Bùi Công Trừng, Quận 12",
      "lat": 10.897721,
      "lng": 106.689101,
      "stationType": 1
    },
    {
      "stationId": 75,
      "stationOrder": 51,
      "stationDirection": 1,
      "routeId": 3,
      "stationName": "Thạnh Xuân",
      "pathPoints": "106.6891009899967,10.897721241026513 106.68910217,10.89772129 106.68910217,10.89772129 106.68910217,10.89772129 106.68887329,10.89866352 106.68674469,10.89776325 106.68461609,10.89676762 106.68294525,10.89615917 106.68126678,10.89555073 106.67926025,10.89505291 106.67725372,10.89455509 106.67532349,10.89396 106.67339325,10.89336491 106.67342377,10.89288044 106.67342377,10.89288044",
      "stationAddress": "Thửa đất số 413 tờ bản đồ số 04, phường Thạnh Xuân, Quận 12, đường Thạnh Xuân 52, Quận 12",
      "lat": 10.89288,
      "lng": 106.673427,
      "stationType": 1
    }
  ]
}